stockpiler/__init__.py
stockpiler/__main__.py
stockpiler/nornir_conf.yaml
stockpiler/ssh_config
stockpiler/processors/__init__.py
stockpiler/processors/process_stockpiles.py
stockpiler/tasks/__init__.py
stockpiler/tasks/stockpile/__init__.py
stockpiler/tasks/stockpile/stockpile_base.py
stockpiler/tasks/stockpile/stockpile_cisco.py
stockpiler/tasks/stockpile/stockpile_f5.py
stockpiler/tasks/stockpile/stockpile_results.py
stockpiler-0.5.3.dist-info/LICENSE
stockpiler-0.5.3.dist-info/METADATA
stockpiler-0.5.3.dist-info/WHEEL
stockpiler-0.5.3.dist-info/entry_points.txt
stockpiler-0.5.3.dist-info/top_level.txt
stockpiler-0.5.3.dist-info/RECORD
